Workbook

Sheet Sales_Data
A1: SALES FORECASTING — Historical Data (24 Months)
A2: Record_ID | B2: Month | C2: Month_Num | D2: Product | E2: Region | F2: Units_Sold | G2: Unit_Price_INR | H2: Revenue_INR
A3: S0001 | B3: Jan 2023 | C3: 1 | D3: Product A | E3: North | F3: 112 | G3: 2429.53 | H3: =F3*G3 -> 272107.36
A4: S0002 | B4: Jan 2023 | C4: 1 | D4: Product A | E4: South | F4: 94 | G4: 2560.37 | H4: =F4*G4 -> 240674.78
A5: S0003 | B5: Jan 2023 | C5: 1 | D5: Product A | E5: East | F5: 97 | G5: 2514.35 | H5: =F5*G5 -> 243891.95
A6: S0004 | B6: Jan 2023 | C6: 1 | D6: Product A | E6: West | F6: 94 | G6: 2323.2 | H6: =F6*G6 -> 218380.8
A7: S0005 | B7: Jan 2023 | C7: 1 | D7: Product A | E7: Central | F7: 75 | G7: 2315 | H7: =F7*G7 -> 173625
A8: S0006 | B8: Jan 2023 | C8: 1 | D8: Product B | E8: North | F8: 110 | G8: 3910.94 | H8: =F8*G8 -> 430203.4
A9: S0007 | B9: Jan 2023 | C9: 1 | D9: Product B | E9: South | F9: 123 | G9: 4149.28 | H9: =F9*G9 -> 510361.44
A10: S0008 | B10: Jan 2023 | C10: 1 | D10: Product B | E10: East | F10: 92 | G10: 3947.19 | H10: =F10*G10 -> 363141.48
A11: S0009 | B11: Jan 2023 | C11: 1 | D11: Product B | E11: West | F11: 108 | G11: 4285.64 | H11: =F11*G11 -> 462849.12
A12: S0010 | B12: Jan 2023 | C12: 1 | D12: Product B | E12: Central | F12: 74 | G12: 4251.81 | H12: =F12*G12 -> 314633.94
A13: S0011 | B13: Jan 2023 | C13: 1 | D13: Product C | E13: North | F13: 108 | G13: 1937.16 | H13: =F13*G13 -> 209213.28
A14: S0012 | B14: Jan 2023 | C14: 1 | D14: Product C | E14: South | F14: 103 | G14: 1903.24 | H14: =F14*G14 -> 196033.72
... A602: S0600 | B602: Dec 2024 | C602: 24 | D602: Product E | E602: Central | F602: 124 | G602: 2884.71 | H602: =F602*G602 -> 357704.04

Sheet Monthly_Revenue
A1: MONTHLY REVENUE SUMMARY & FORECAST
A2: Month | B2: Month_Num | C2: Total_Revenue_INR | D2: MoM_Growth_% | E2: 3M_Moving_Avg_INR | F2: Forecast_Next_Month_INR
A3: Jan 2023 | B3: 1 | C3: =SUMIF(Sales_Data!B3:B602,A3,Sales_Data!H3:H602) -> 8807887.2
A4: Feb 2023 | B4: 2 | C4: =SUMIF(Sales_Data!B3:B602,A4,Sales_Data!H3:H602) -> 9661762 | D4: =IF(C3>0,(C4-C3)/C3,"") -> 0.096944341
A5: Mar 2023 | B5: 3 | C5: =SUMIF(Sales_Data!B3:B602,A5,Sales_Data!H3:H602) -> 9515133.6 | D5: =IF(C4>0,(C5-C4)/C4,"") -> -0.01517616 | E5: =AVERAGE(C3:C5) -> 9328260.9 | F5: =FORECAST(B5+1,C3:C5,B3:B5) -> 10035507
A6: Apr 2023 | B6: 4 | C6: =SUMIF(Sales_Data!B3:B602,A6,Sales_Data!H3:H602) -> 10538756 | D6: =IF(C5>0,(C6-C5)/C5,"") -> 0.1075784 | E6: =AVERAGE(C4:C6) -> 9905217.3 | F6: =FORECAST(B6+1,C3:C6,B3:B6) -> 10892380
A7: May 2023 | B7: 5 | C7: =SUMIF(Sales_Data!B3:B602,A7,Sales_Data!H3:H602) -> 11063608 | D7: =IF(C6>0,(C7-C6)/C6,"") -> 0.049802045 | E7: =AVERAGE(C5:C7) -> 10372499 | F7: =FORECAST(B7+1,C3:C7,B3:B7) -> 11533960
A8: Jun 2023 | B8: 6 | C8: =SUMIF(Sales_Data!B3:B602,A8,Sales_Data!H3:H602) -> 11340657 | D8: =IF(C7>0,(C8-C7)/C7,"") -> 0.025041474 | E8: =AVERAGE(C6:C8) -> 10981007 | F8: =FORECAST(B8+1,C3:C8,B3:B8) -> 11943935
A9: Jul 2023 | B9: 7 | C9: =SUMIF(Sales_Data!B3:B602,A9,Sales_Data!H3:H602) -> 11331074 | D9: =IF(C8>0,(C9-C8)/C8,"") -> -0.00084501541 | E9: =AVERAGE(C7:C9) -> 11245113 | F9: =FORECAST(B9+1,C3:C9,B3:B9) -> 12104958
A10: Aug 2023 | B10: 8 | C10: =SUMIF(Sales_Data!B3:B602,A10,Sales_Data!H3:H602) -> 11514525 | D10: =IF(C9>0,(C10-C9)/C9,"") -> 0.016190103 | E10: =AVERAGE(C8:C10) -> 11395419 | F10: =FORECAST(B10+1,C3:C10,B3:B10) -> 12255307
A11: Sep 2023 | B11: 9 | C11: =SUMIF(Sales_Data!B3:B602,A11,Sales_Data!H3:H602) -> 11892413 | D11: =IF(C10>0,(C11-C10)/C10,"") -> 0.032818351 | E11: =AVERAGE(C9:C11) -> 11579337 | F11: =FORECAST(B11+1,C3:C11,B3:B11) -> 12490383
A12: Oct 2023 | B12: 10 | C12: =SUMIF(Sales_Data!B3:B602,A12,Sales_Data!H3:H602) -> 12495180 | D12: =IF(C11>0,(C12-C11)/C11,"") -> 0.050685021 | E12: =AVERAGE(C10:C12) -> 11967373 | F12: =FORECAST(B12+1,C3:C12,B3:B12) -> 12864472
A13: Nov 2023 | B13: 11 | C13: =SUMIF(Sales_Data!B3:B602,A13,Sales_Data!H3:H602) -> 12830775 | D13: =IF(C12>0,(C13-C12)/C12,"") -> 0.026857958 | E13: =AVERAGE(C11:C13) -> 12406123 | F13: =FORECAST(B13+1,C3:C13,B3:B13) -> 13224650
A14: Dec 2023 | B14: 12 | C14: =SUMIF(Sales_Data!B3:B602,A14,Sales_Data!H3:H602) -> 13028944 | D14: =IF(C13>0,(C14-C13)/C13,"") -> 0.015444785 | E14: =AVERAGE(C12:C14) -> 12784966 | F14: =FORECAST(B14+1,C3:C14,B3:B14) -> 13530314
A15: Jan 2024 | B15: 13 | C15: =SUMIF(Sales_Data!B3:B602,A15,Sales_Data!H3:H602) -> 8969438.2 | D15: =IF(C14>0,(C15-C14)/C14,"") -> -0.31157596 | E15: =AVERAGE(C13:C15) -> 11609719 | F15: =FORECAST(B15+1,C3:C15,B3:B15) -> 12490340
A16: Feb 2024 | B16: 14 | C16: =SUMIF(Sales_Data!B3:B602,A16,Sales_Data!H3:H602) -> 9569035.7 | D16: =IF(C15>0,(C16-C15)/C15,"") -> 0.066848949 | E16: =AVERAGE(C14:C16) -> 10522473 | F16: =FORECAST(B16+1,C3:C16,B3:B16) -> 11868696
A17: Mar 2024 | B17: 15 | C17: =SUMIF(Sales_Data!B3:B602,A17,Sales_Data!H3:H602) -> 10107561 | D17: =IF(C16>0,(C17-C16)/C16,"") -> 0.056277882 | E17: =AVERAGE(C15:C17) -> 9548678.2 | F17: =FORECAST(B17+1,C3:C17,B3:B17) -> 11528608
A18: Apr 2024 | B18: 16 | C18: =SUMIF(Sales_Data!B3:B602,A18,Sales_Data!H3:H602) -> 10198060 | D18: =IF(C17>0,(C18-C17)/C17,"") -> 0.008953636 | E18: =AVERAGE(C16:C18) -> 9958218.9 | F18: =FORECAST(B18+1,C3:C18,B3:B18) -> 11281491
A19: May 2024 | B19: 17 | C19: =SUMIF(Sales_Data!B3:B602,A19,Sales_Data!H3:H602) -> 10488544 | D19: =IF(C18>0,(C19-C18)/C18,"") -> 0.028484183 | E19: =AVERAGE(C17:C19) -> 10264722 | F19: =FORECAST(B19+1,C3:C19,B3:B19) -> 11151084
A20: Jun 2024 | B20: 18 | C20: =SUMIF(Sales_Data!B3:B602,A20,Sales_Data!H3:H602) -> 10699306 | D20: =IF(C19>0,(C20-C19)/C19,"") -> 0.0200945 | E20: =AVERAGE(C18:C20) -> 10461970 | F20: =FORECAST(B20+1,C3:C20,B3:B20) -> 11091310
A21: Jul 2024 | B21: 19 | C21: =SUMIF(Sales_Data!B3:B602,A21,Sales_Data!H3:H602) -> 11673788 | D21: =IF(C20>0,(C21-C20)/C20,"") -> 0.091079033 | E21: =AVERAGE(C19:C21) -> 10953879 | F21: =FORECAST(B21+1,C3:C21,B3:B21) -> 11246633
A22: Aug 2024 | B22: 20 | C22: =SUMIF(Sales_Data!B3:B602,A22,Sales_Data!H3:H602) -> 11246387 | D22: =IF(C21>0,(C22-C21)/C21,"") -> -0.03661201 | E22: =AVERAGE(C20:C22) -> 11206494 | F22: =FORECAST(B22+1,C3:C22,B3:B22) -> 11288476
A23: Sep 2024 | B23: 21 | C23: =SUMIF(Sales_Data!B3:B602,A23,Sales_Data!H3:H602) -> 12653777 | D23: =IF(C22>0,(C23-C22)/C22,"") -> 0.1251415 | E23: =AVERAGE(C21:C23) -> 11857984 | F23: =FORECAST(B23+1,C3:C23,B3:B23) -> 11590422
A24: Oct 2024 | B24: 22 | C24: =SUMIF(Sales_Data!B3:B602,A24,Sales_Data!H3:H602) -> 12310929 | D24: =IF(C23>0,(C24-C23)/C23,"") -> -0.027094487 | E24: =AVERAGE(C22:C24) -> 12070365 | F24: =FORECAST(B24+1,C3:C24,B3:B24) -> 11781044
A25: Nov 2024 | B25: 23 | C25: =SUMIF(Sales_Data!B3:B602,A25,Sales_Data!H3:H602) -> 12779131 | D25: =IF(C24>0,(C25-C24)/C24,"") -> 0.038031372 | E25: =AVERAGE(C23:C25) -> 12581279 | F25: =FORECAST(B25+1,C3:C25,B3:B25) -> 12022788
A26: Dec 2024 | B26: 24 | C26: =SUMIF(Sales_Data!B3:B602,A26,Sales_Data!H3:H602) -> 13345139 | D26: =IF(C25>0,(C26-C25)/C25,"") -> 0.044291607 | E26: =AVERAGE(C24:C26) -> 12811733 | F26: =FORECAST(B26+1,C3:C26,B3:B26) -> 12322192
A27: TOTAL / AVG | C27: =SUM(C3:C26) -> 2.6806181e+08 | D27: =AVERAGE(D4:D26) -> 0.022141805 | E27: =AVERAGE(E5:E26) -> 11173310

Sheet Product_Region_Summary
A1: PRODUCT & REGION WISE REVENUE SUMMARY
A2: Product | B2: North | C2: South | D2: East | E2: West | F2: Central | G2: Grand Total (INR)
A3: Product A | B3: =SUMIFS(Sales_Data!H3:H602,Sales_Data!D3:D602,A3,Sales_Data!E3:E602,B2) -> 9179551.4 | C3: =SUMIFS(Sales_Data!H3:H602,Sales_Data!D3:D602,A3,Sales_Data!E3:E602,C2) -> 8149875.3 | D3: =SUMIFS(Sales_Data!H3:H602,Sales_Data!D3:D602,A3,Sales_Data!E3:E602,D2) -> 7538172.2 | E3: =SUMIFS(Sales_Data!H3:H602,Sales_Data!D3:D602,A3,Sales_Data!E3:E602,E2) -> 6817985.1 | F3: =SUMIFS(Sales_Data!H3:H602,Sales_Data!D3:D602,A3,Sales_Data!E3:E602,F2) -> 5712561.8 | G3: =SUM(B3:F3) -> 37398146
A4: Product B | B4: =SUMIFS(Sales_Data!H3:H602,Sales_Data!D3:D602,A4,Sales_Data!E3:E602,B2) -> 15757672 | C4: =SUMIFS(Sales_Data!H3:H602,Sales_Data!D3:D602,A4,Sales_Data!E3:E602,C2) -> 13484868 | D4: =SUMIFS(Sales_Data!H3:H602,Sales_Data!D3:D602,A4,Sales_Data!E3:E602,D2) -> 12315706 | E4: =SUMIFS(Sales_Data!H3:H602,Sales_Data!D3:D602,A4,Sales_Data!E3:E602,E2) -> 11737668 | F4: =SUMIFS(Sales_Data!H3:H602,Sales_Data!D3:D602,A4,Sales_Data!E3:E602,F2) -> 9108186.5 | G4: =SUM(B4:F4) -> 62404101
A5: Product C | B5: =SUMIFS(Sales_Data!H3:H602,Sales_Data!D3:D602,A5,Sales_Data!E3:E602,B2) -> 6959886.8 | C5: =SUMIFS(Sales_Data!H3:H602,Sales_Data!D3:D602,A5,Sales_Data!E3:E602,C2) -> 5841154.7 | D5: =SUMIFS(Sales_Data!H3:H602,Sales_Data!D3:D602,A5,Sales_Data!E3:E602,D2) -> 5179434.7 | E5: =SUMIFS(Sales_Data!H3:H602,Sales_Data!D3:D602,A5,Sales_Data!E3:E602,E2) -> 4824343.3 | F5: =SUMIFS(Sales_Data!H3:H602,Sales_Data!D3:D602,A5,Sales_Data!E3:E602,F2) -> 3985499.9 | G5: =SUM(B5:F5) -> 26790319
A6: Product D | B6: =SUMIFS(Sales_Data!H3:H602,Sales_Data!D3:D602,A6,Sales_Data!E3:E602,B2) -> 23017921 | C6: =SUMIFS(Sales_Data!H3:H602,Sales_Data!D3:D602,A6,Sales_Data!E3:E602,C2) -> 21232062 | D6: =SUMIFS(Sales_Data!H3:H602,Sales_Data!D3:D602,A6,Sales_Data!E3:E602,D2) -> 18723222 | E6: =SUMIFS(Sales_Data!H3:H602,Sales_Data!D3:D602,A6,Sales_Data!E3:E602,E2) -> 17773551 | F6: =SUMIFS(Sales_Data!H3:H602,Sales_Data!D3:D602,A6,Sales_Data!E3:E602,F2) -> 14126094 | G6: =SUM(B6:F6) -> 94872850
A7: Product E | B7: =SUMIFS(Sales_Data!H3:H602,Sales_Data!D3:D602,A7,Sales_Data!E3:E602,B2) -> 11728082 | C7: =SUMIFS(Sales_Data!H3:H602,Sales_Data!D3:D602,A7,Sales_Data!E3:E602,C2) -> 10217666 | D7: =SUMIFS(Sales_Data!H3:H602,Sales_Data!D3:D602,A7,Sales_Data!E3:E602,D2) -> 9096483.2 | E7: =SUMIFS(Sales_Data!H3:H602,Sales_Data!D3:D602,A7,Sales_Data!E3:E602,E2) -> 8533199.3 | F7: =SUMIFS(Sales_Data!H3:H602,Sales_Data!D3:D602,A7,Sales_Data!E3:E602,F2) -> 7020965.8 | G7: =SUM(B7:F7) -> 46596396
A8: Total | B8: =SUM(B3:B7) -> 66643113 | C8: =SUM(C3:C7) -> 58925627 | D8: =SUM(D3:D7) -> 52853018 | E8: =SUM(E3:E7) -> 49686746 | F8: =SUM(F3:F7) -> 39953308 | G8: =SUM(G3:G7) -> 2.6806181e+08

Sheet YoY_Growth
A1: YEAR-ON-YEAR GROWTH ANALYSIS
A2: Product | B2: Revenue FY2023 (INR) | C2: Revenue FY2024 (INR) | D2: YoY Growth (INR) | E2: YoY Growth %
A3: Product A | B3: =SUMPRODUCT((Sales_Data!D3:D602=A3)*(Sales_Data!C3:C602<=12)*Sales_Data!H3:H602) -> 18620522 | C3: =SUMPRODUCT((Sales_Data!D3:D602=A3)*(Sales_Data!C3:C602>12)*Sales_Data!H3:H602) -> 18777624 | D3: =C3-B3 -> 157101.47 | E3: =IF(B3>0,(C3-B3)/B3,"") -> 0.0084370067
A4: Product B | B4: =SUMPRODUCT((Sales_Data!D3:D602=A4)*(Sales_Data!C3:C602<=12)*Sales_Data!H3:H602) -> 31273520 | C4: =SUMPRODUCT((Sales_Data!D3:D602=A4)*(Sales_Data!C3:C602>12)*Sales_Data!H3:H602) -> 31130581 | D4: =C4-B4 -> -142938.9 | E4: =IF(B4>0,(C4-B4)/B4,"") -> -0.0045706048
A5: Product C | B5: =SUMPRODUCT((Sales_Data!D3:D602=A5)*(Sales_Data!C3:C602<=12)*Sales_Data!H3:H602) -> 13502216 | C5: =SUMPRODUCT((Sales_Data!D3:D602=A5)*(Sales_Data!C3:C602>12)*Sales_Data!H3:H602) -> 13288103 | D5: =C5-B5 -> -214113.64 | E5: =IF(B5>0,(C5-B5)/B5,"") -> -0.015857666
A6: Product D | B6: =SUMPRODUCT((Sales_Data!D3:D602=A6)*(Sales_Data!C3:C602<=12)*Sales_Data!H3:H602) -> 47395919 | C6: =SUMPRODUCT((Sales_Data!D3:D602=A6)*(Sales_Data!C3:C602>12)*Sales_Data!H3:H602) -> 47476931 | D6: =C6-B6 -> 81012.75 | E6: =IF(B6>0,(C6-B6)/B6,"") -> 0.0017092769
A7: Product E | B7: =SUMPRODUCT((Sales_Data!D3:D602=A7)*(Sales_Data!C3:C602<=12)*Sales_Data!H3:H602) -> 23228539 | C7: =SUMPRODUCT((Sales_Data!D3:D602=A7)*(Sales_Data!C3:C602>12)*Sales_Data!H3:H602) -> 23367857 | D7: =C7-B7 -> 139317.89 | E7: =IF(B7>0,(C7-B7)/B7,"") -> 0.0059977034
A8: TOTAL | B8: =SUM(B3:B7) -> 1.3402072e+08 | C8: =SUM(C3:C7) -> 1.340411e+08 | D8: =SUM(D3:D7) -> 20379.57 | E8: =IF(B8>0,(C8-B8)/B8,"") -> 0.00015206283
